win_console/__init__.py
win_console/core.py
win_console/exception.py
win_console/utils.py
win_console-0.0.5.dist-info/LICENSE
win_console-0.0.5.dist-info/METADATA
win_console-0.0.5.dist-info/WHEEL
win_console-0.0.5.dist-info/top_level.txt
win_console-0.0.5.dist-info/RECORD
