Metadata-Version: 2.1
Name: win-console
Version: 0.0.5
Summary: A Windows Console Helper
Author: W.M
Author-email: python_zhong@qq.com
License: UNKNOWN
Platform: UNKNOWN
Classifier: Programming Language :: Python :: 3
Classifier: License :: OSI Approved :: MIT License
Classifier: Operating System :: OS Independent
Requires-Python: >=3.6
License-File: LICENSE
